sciagraph_report-2024.8.0.dist-info/METADATA
sciagraph_report-2024.8.0.dist-info/WHEEL
sciagraph_report/__init__.py
sciagraph_report/licenses.html
sciagraph_report/__main__.py
sciagraph_report-2024.8.0.data/scripts/sciagraph-report
sciagraph_report-2024.8.0.dist-info/RECORD
