Metadata-Version: 2.1
Name: sciagraph-report
Version: 2024.8.0
Classifier: Programming Language :: Rust
Classifier: Programming Language :: Python :: Implementation :: CPython
Classifier: Programming Language :: Python :: Implementation :: PyPy
Requires-Dist: importlib_metadata; python_version < '3.8'
License: LicenseRef-Hyphenated-Proprietary
Requires-Python: >=3.7
